async_imgkit
