Metadata-Version: 2.1
Name: async-imgkit
Version: 0.0.5
Summary: Wkhtmltopdf python wrapper to convert html to image using the webkit rendering engine and qt
Home-page: https://github.com/guilhermef/async-imgkit
Author: guilhermef
Author-email: guivideojob@gmail.com
License: MIT
Download-URL: https://github.com/guilhermef/async-imgkit
Platform: UNKNOWN
Classifier: Programming Language :: Python
Classifier: Programming Language :: Python :: 3.6
Classifier: Programming Language :: Python :: 3.7
Classifier: Programming Language :: Python :: 3.8
Classifier: Programming Language :: Python :: 3.9
Classifier: Topic :: Text Processing
Classifier: Topic :: Text Processing :: General
Classifier: Topic :: Text Processing :: Markup
Classifier: Topic :: Text Processing :: Markup :: HTML
Classifier: Topic :: Text Processing :: Markup :: XML
Classifier: Topic :: Utilities
Provides-Extra: tests
